{
  "acceptableImpedanceThreshold": 1.0,
  "batlabToolkitGUIVersion": "0.0.1",
  "cellPlaylistName": "Breakin",
  "chargeCurrentSafetyCutoff": 4.096,
  "chargeRate": 2.75,
  "chargeTemperatureCutoff": 60,
  "dischargeCurrentSafetyCutoff": 4.096,
  "dischargeRate": 2.5,
  "dischargeTemperatureCutoff": 80,
  "highVoltageCutoff": 4.2675,
  "impedanceReportingPeriod": 120,
  "lowVoltageCutoff": 2.4325,
  "numMeasurementCycles": 1,
  "numWarmupCycles": 0,
  "reportingPeriod": 1.0,
  "restPeriod": 300,
  "sineWaveFrequency": 39.0625,
  "sineWaveMagnitude": 2.0,
  "storageDischarge": 1,
  "storageDischargeVoltage": 3.7,
	"trickleEnable": 1,
	"pulseEnable": 0,
	"trickleDischrgEngageVoltage": 2.8 ,
	"trickleChrgEngageVoltage": 4.05,
	"trickleChrgRate": 0.75,
	"trickleDischrgRate": 0.75

}